actions/__init__.py
actions/dispatch_actions.py
actions/first_interaction.py
actions/format_python_docstrings.py
actions/review_pr.py
actions/scan_prs.py
actions/summarize_pr.py
actions/summarize_release.py
actions/update_file_headers.py
actions/update_markdown_code_blocks.py
actions/utils/__init__.py
actions/utils/common_utils.py
actions/utils/github_utils.py
actions/utils/openai_utils.py
actions/utils/version_utils.py
ultralytics_actions-0.2.12.dist-info/licenses/LICENSE
ultralytics_actions-0.2.12.dist-info/METADATA
ultralytics_actions-0.2.12.dist-info/WHEEL
ultralytics_actions-0.2.12.dist-info/entry_points.txt
ultralytics_actions-0.2.12.dist-info/top_level.txt
ultralytics_actions-0.2.12.dist-info/RECORD
